nvitop_exporter/__init__.py
nvitop_exporter/__main__.py
nvitop_exporter/cli.py
nvitop_exporter/exporter.py
nvitop_exporter/utils.py
nvitop_exporter/version.py
nvitop_exporter-1.6.1.dist-info/licenses/LICENSE
nvitop_exporter-1.6.1.dist-info/METADATA
nvitop_exporter-1.6.1.dist-info/WHEEL
nvitop_exporter-1.6.1.dist-info/entry_points.txt
nvitop_exporter-1.6.1.dist-info/top_level.txt
nvitop_exporter-1.6.1.dist-info/RECORD
