Metadata-Version: 2.4
Name: nvitop-exporter
Version: 1.6.1
Summary: Prometheus exporter built on top of `nvitop`.
Author-email: Xuehai Pan <XuehaiPan@pku.edu.cn>
License: Apache-2.0
Project-URL: Homepage, https://github.com/XuehaiPan/nvitop
Project-URL: Repository, https://github.com/XuehaiPan/nvitop
Project-URL: Documentation, https://nvitop.readthedocs.io
Project-URL: Bug Report, https://github.com/XuehaiPan/nvitop/issues
Keywords: nvidia,nvidia-smi,NVIDIA,NVML,CUDA,GPU,top,monitoring,prometheus,Prometheus,grafana,Grafana
Classifier: Development Status :: 5 - Production/Stable
Classifier: License :: OSI Approved :: Apache Software License
Classifier: Programming Language :: Python :: 3
Classifier: Programming Language :: Python :: 3.8
Classifier: Programming Language :: Python :: 3.9
Classifier: Programming Language :: Python :: 3.10
Classifier: Programming Language :: Python :: 3.11
Classifier: Programming Language :: Python :: 3.12
Classifier: Programming Language :: Python :: 3.13
Classifier: Programming Language :: Python :: 3.14
Classifier: Operating System :: Microsoft :: Windows
Classifier: Operating System :: POSIX :: Linux
Classifier: Environment :: GPU
Classifier: Environment :: GPU :: NVIDIA CUDA
Classifier: Intended Audience :: Developers
Classifier: Intended Audience :: End Users/Desktop
Classifier: Intended Audience :: System Administrators
Classifier: Topic :: System :: Hardware
Classifier: Topic :: System :: Monitoring
Classifier: Topic :: System :: Systems Administration
Classifier: Topic :: Utilities
Requires-Python: >=3.8
License-File: LICENSE
Requires-Dist: nvitop~=1.6.1
Requires-Dist: prometheus-client>=0.4.0
Dynamic: license-file
